{
  "_meta": {
    "count": 2
  },
  "samples": [
    {
      "id": "NARR-HEPAN-001",
      "title": "合盘分析结构样例（黄×路）",
      "source": "文墨天机/合盘.docx",
      "domain": "ziwei_compat",
      "trust_level": "experience_inference",
      "ui_label": "经验推断",
      "excerpt": "这不是一对平静的夫妻，而是一对在动荡中不断磨合、重塑彼此的伴侣。你们的结合，是命运最精巧的安排。两个内心都极度缺乏安全感的人，用一种近乎残酷的方式，成为了彼此的依靠和功课。\n\n**1. 五行层面：一种极致的互补与牵制**\n\n* **黄**：**戊辰 戊午 辛亥 辛卯**，土旺身强，急需木来疏通，水来滋润。\n* **路**：**癸酉 乙卯 丙戌 壬辰**，木火通明，印旺身强，急需土来泄火，金来制木。\n* 黄是路的一堆“厚土”，能吸纳她所有过剩的精力和情绪（火生土）；路是黄的一棵“劲木”，能唤醒他被厚土压抑的生命力（木克土）。黄的路，是她的定心丸；路的黄，是他的活力源。**在生理和能量层面，你们是彼此的“药”。**\n\n**2. 十神层面：一段极深的灵魂契约**\n\n* **路对黄**：路是丙火，黄是辛金，**丙辛合**。这是天干五合中最具情感色彩的一对，代表迷恋、吸引、灵魂的碰撞。路看黄，总带着一种“说不清为什么，但就是被你吸引”的滤镜。黄的路，是她的“正财”，代表她想要稳定下来的归宿。\n* **黄对路**：黄看路，则是“正官”。正官代表责任、约束、还有那么一点点怕。黄天生会被路“管着”，也心甘情愿地被她管。因为在他的内心深处，他需要一个清晰的目标和规则（正官），来对抗自己的散漫和惰性。\n\n**3. 地支互动：家宅不宁，却因家成事**\n\n* **卯戌合，辰酉合，卯酉冲**：你们的夫妻宫（黄亥、路戌）和各自根基，形成了极其复杂的互动。路的月柱卯木，是黄的时柱，也是夫妻宫的“情敌”（卯戌合，路的内心总有别的想法）。黄的年柱辰土，与路的年柱酉金六合，又与时支卯木相冲。这代表**你们的结合，是两种家庭、两种观念的剧烈碰撞，会带来无尽的争吵（卯酉冲），但又因为孩子（辰酉合，子女宫被合动）而牢牢绑定在一起。**\n\n**二、 紫微斗数合盘：一个“因家而起”的业力场**\n\n**1. 关键宫位互动**\n\n* **黄田宅宫（来因宫）：天机化忌，右弼化科，擎羊**。这是黄一生的不安之源，也是你们婚姻的核心战场。\n* **路子女宫：紫微天府，文曲**。这是路的骄傲，也是她的执念所在。\n* 两人的田宅宫和子女宫严重交织。你们的婚姻，从一开始就与**房子、家庭、孩子**这三件事深度绑定。你们的争吵，大半是因为家事、因为孩子、因为房子。\n\n**2. 核心业力点**\n\n* **路对黄的影响**：路的贪狼忌入黄的父母宫，巨门忌冲黄的疾厄。路的存在，会深刻地影响黄与他的原生家庭（尤其母亲）的关系，让黄左右为难。同时，她那张不饶人的嘴（巨门），会直接攻击黄最脆弱的精神和身体。\n* **黄对路的影响**：黄的天机忌，让路的福德宫（精神）感到无比焦虑。他那种“闷葫芦”一样的性格，和对未来的过度担忧，会让路这个本来就想得多的人，更加烦躁。\n\n**三、 子女分析：你们共同的考验与骄傲**\n\n**关于孩子：**",
      "tags": [
        "合盘",
        "夫妻",
        "子女",
        "大限"
      ]
    },
    {
      "id": "NARR-ZW-001",
      "title": "紫微段落叙事样例（华倩盘）",
      "source": "文墨天机/华.docx",
      "domain": "ziwei_palace",
      "trust_level": "experience_inference",
      "ui_label": "经验推断",
      "excerpt": "此盘最大的特点，是**命宫府相朝垣，福德贪狼化忌**的巨大反差。你有一个高贵的「壳」，但里面住着一个「骚动不安的灵魂」。官禄宫武曲天相，是典型的「财荫夹印」格，在大型金融机构或公家单位做财务管理，是正途。",
      "tags": [
        "命宫",
        "福德",
        "官禄",
        "财帛"
      ]
    }
  ]
}
